roquick_api/__init__.py
roquick_api/roquick_api.py
roquick_api-0.0.3b0.dist-info/licenses/License
roquick_api-0.0.3b0.dist-info/METADATA
roquick_api-0.0.3b0.dist-info/WHEEL
roquick_api-0.0.3b0.dist-info/top_level.txt
roquick_api-0.0.3b0.dist-info/RECORD
